excelart/__init__.py
excelart/excelart.py
excelart/pet.py
excelart/setup.py
excelart-0.1.2.dist-info/METADATA
excelart-0.1.2.dist-info/WHEEL
excelart-0.1.2.dist-info/top_level.txt
excelart-0.1.2.dist-info/RECORD
