Metadata-Version: 2.1
Name: excelart
Version: 0.1.2
Summary: A package to convert excel data to image
Home-page: https://github.com/ujwalrajeev/excelart
Author: Ujwal Rajeev
Author-email: ujwalrajeev@gmail.com
Classifier: Development Status :: 3 - Alpha
Classifier: Intended Audience :: Developers
Classifier: License :: OSI Approved :: MIT License
Classifier: Programming Language :: Python :: 3
Classifier: Programming Language :: Python :: 3.6
Classifier: Programming Language :: Python :: 3.7
Classifier: Programming Language :: Python :: 3.8
Requires-Python: >=3.6
Requires-Dist: openpyxl
Requires-Dist: Pillow
